[
  {
    "id": 1,
    "loge_id": "M1-C1-B1-L1",
    "mur": 1,
    "col_beton": 1,
    "bloc": 1,
    "loge": 1,
    "domaine": "François Cazin",
    "appellation": "Chevergny",
    "millesime": "2022",
    "boire_a_partir": null,
    "boire_avant": null,
    "couleur": "blanc",
    "prix_unit": 8.0,
    "quantite": 6,
    "bottles_haut": 3,
    "bottles_bas": 3,
    "notes": "",
    "created_at": "2026-03-08 08:21:27",
    "groupe_id": "2a5a3bf2",
    "cuvee": ""
  },
  {
    "id": 2,
    "loge_id": "M1-C1-B1-L2",
    "mur": 1,
    "col_beton": 1,
    "bloc": 1,
    "loge": 2,
    "domaine": "Domaine Dujardin",
    "appellation": "Auxey Duresses",
    "millesime": "2016",
    "boire_a_partir": 2022,
    "boire_avant": 2022,
    "couleur": "rouge",
    "prix_unit": 17.0,
    "quantite": 3,
    "bottles_haut": 3,
    "bottles_bas": 3,
    "notes": "",
    "created_at": "2026-03-08 08:21:27",
    "groupe_id": "2a5a3bf2",
    "cuvee": ""
  },
  {
    "id": 3,
    "loge_id": "M1-C1-B1-L3",
    "mur": 1,
    "col_beton": 1,
    "bloc": 1,
    "loge": 3,
    "domaine": "Domaine Deschamps",
    "appellation": "Poully Fumé V V",
    "millesime": "2022",
    "boire_a_partir": 2026,
    "boire_avant": 2026,
    "couleur": "blanc",
    "prix_unit": 15.0,
    "quantite": 3,
    "bottles_haut": 2,
    "bottles_bas": 0,
    "notes": "",
    "created_at": "2026-03-08 08:21:27",
    "groupe_id": "2a5a3bf2",
    "cuvee": ""
  },
  {
    "id": 4,
    "loge_id": "M1-C1-B1-L4",
    "mur": 1,
    "col_beton": 1,
    "bloc": 1,
    "loge": 4,
    "domaine": "Domaine A.Bonhomme",
    "appellation": "Viré Clessé",
    "millesime": "2020",
    "boire_a_partir": 2024,
    "boire_avant": null,
    "couleur": "blanc",
    "prix_unit": 15.0,
    "quantite": 4,
    "bottles_haut": 1,
    "bottles_bas": 3,
    "notes": "",
    "created_at": "2026-03-08 08:21:27",
    "groupe_id": null
  },
  {
    "id": 5,
    "loge_id": "M1-C1-B2-L1",
    "mur": 1,
    "col_beton": 1,
    "bloc": 2,
    "loge": 1,
    "domaine": "Domaine Deschamps",
    "appellation": "Poully Fumé V V",
    "millesime": "2022",
    "boire_a_partir": 2026,
    "boire_avant": null,
    "couleur": "blanc",
    "prix_unit": 15.0,
    "quantite": 3,
    "bottles_haut": 0,
    "bottles_bas": 3,
    "notes": "",
    "created_at": "2026-03-08 08:21:27",
    "groupe_id": null
  },
  {
    "id": 6,
    "loge_id": "M1-C1-B2-L2",
    "mur": 1,
    "col_beton": 1,
    "bloc": 2,
    "loge": 2,
    "domaine": "Domaine Deschamps",
    "appellation": "Pouilly Fumé Vinealis",
    "millesime": "2021",
    "boire_a_partir": 2026,
    "boire_avant": null,
    "couleur": "blanc",
    "prix_unit": 17.0,
    "quantite": 6,
    "bottles_haut": 3,
    "bottles_bas": 3,
    "notes": "",
    "created_at": "2026-03-08 08:21:27",
    "groupe_id": null
  },
  {
    "id": 7,
    "loge_id": "M1-C1-B2-L3",
    "mur": 1,
    "col_beton": 1,
    "bloc": 2,
    "loge": 3,
    "domaine": "Bourgogne",
    "appellation": "Plénitude",
    "millesime": "2021",
    "boire_a_partir": null,
    "boire_avant": null,
    "couleur": "rouge",
    "prix_unit": 12.0,
    "quantite": 4,
    "bottles_haut": 3,
    "bottles_bas": 1,
    "notes": "",
    "created_at": "2026-03-08 08:21:27",
    "groupe_id": null
  },
  {
    "id": 8,
    "loge_id": "M1-C1-B2-L4",
    "mur": 1,
    "col_beton": 1,
    "bloc": 2,
    "loge": 4,
    "domaine": "Domaine Cheveau",
    "appellation": "Pouilly Fuissé",
    "millesime": "2018",
    "boire_a_partir": 2024,
    "boire_avant": null,
    "couleur": "blanc",
    "prix_unit": 16.5,
    "quantite": 3,
    "bottles_haut": 0,
    "bottles_bas": 3,
    "notes": "",
    "created_at": "2026-03-08 08:21:27",
    "groupe_id": null
  },
  {
    "id": 9,
    "loge_id": "M1-C1-B3-L1",
    "mur": 1,
    "col_beton": 1,
    "bloc": 3,
    "loge": 1,
    "domaine": "Vignoble Doublet",
    "appellation": "Cht Tour de Calens Graves",
    "millesime": "2021",
    "boire_a_partir": 2026,
    "boire_avant": null,
    "couleur": "rouge",
    "prix_unit": 12.0,
    "quantite": 6,
    "bottles_haut": 3,
    "bottles_bas": 3,
    "notes": "",
    "created_at": "2026-03-08 08:21:27",
    "groupe_id": null
  },
  {
    "id": 10,
    "loge_id": "M1-C1-B3-L2",
    "mur": 1,
    "col_beton": 1,
    "bloc": 3,
    "loge": 2,
    "domaine": "Domaine Deschamps",
    "appellation": "Poully Fumé Les Loges",
    "millesime": "2021",
    "boire_a_partir": 2025,
    "boire_avant": null,
    "couleur": "blanc",
    "prix_unit": 13.5,
    "quantite": 5,
    "bottles_haut": 2,
    "bottles_bas": 3,
    "notes": "",
    "created_at": "2026-03-08 08:21:27",
    "groupe_id": null
  },
  {
    "id": 11,
    "loge_id": "M1-C1-B3-L3",
    "mur": 1,
    "col_beton": 1,
    "bloc": 3,
    "loge": 3,
    "domaine": "Domaine JJ Girard",
    "appellation": "Savigny les Beaunes",
    "millesime": "2016",
    "boire_a_partir": 2022,
    "boire_avant": null,
    "couleur": "rouge",
    "prix_unit": 18.0,
    "quantite": 6,
    "bottles_haut": 3,
    "bottles_bas": 3,
    "notes": "",
    "created_at": "2026-03-08 08:21:27",
    "groupe_id": null
  },
  {
    "id": 12,
    "loge_id": "M1-C1-B3-L4",
    "mur": 1,
    "col_beton": 1,
    "bloc": 3,
    "loge": 4,
    "domaine": "Domaine Rapet",
    "appellation": "Ladoix Les Vris",
    "millesime": "2020",
    "boire_a_partir": 2025,
    "boire_avant": null,
    "couleur": "rouge",
    "prix_unit": 16.0,
    "quantite": 6,
    "bottles_haut": 3,
    "bottles_bas": 3,
    "notes": "",
    "created_at": "2026-03-08 08:21:27",
    "groupe_id": null
  },
  {
    "id": 13,
    "loge_id": "M1-C1-B4-L1",
    "mur": 1,
    "col_beton": 1,
    "bloc": 4,
    "loge": 1,
    "domaine": "Domaine Deschamps",
    "appellation": "Poully Fumé Les Loges",
    "millesime": "2021",
    "boire_a_partir": 2025,
    "boire_avant": null,
    "couleur": "blanc",
    "prix_unit": 13.5,
    "quantite": 5,
    "bottles_haut": 2,
    "bottles_bas": 3,
    "notes": "",
    "created_at": "2026-03-08 08:21:27",
    "groupe_id": null
  },
  {
    "id": 14,
    "loge_id": "M1-C1-B4-L2",
    "mur": 1,
    "col_beton": 1,
    "bloc": 4,
    "loge": 2,
    "domaine": "Domaine de Bournet",
    "appellation": "Les Ambassadeurs",
    "millesime": "2016",
    "boire_a_partir": 2022,
    "boire_avant": null,
    "couleur": "rouge",
    "prix_unit": 16.0,
    "quantite": 4,
    "bottles_haut": 1,
    "bottles_bas": 3,
    "notes": "",
    "created_at": "2026-03-08 08:21:27",
    "groupe_id": null
  },
  {
    "id": 15,
    "loge_id": "M1-C1-B4-L3",
    "mur": 1,
    "col_beton": 1,
    "bloc": 4,
    "loge": 3,
    "domaine": "Domaine Mattaverne",
    "appellation": "Pouilly Fumé",
    "millesime": "2023",
    "boire_a_partir": null,
    "boire_avant": null,
    "couleur": "blanc",
    "prix_unit": 13.0,
    "quantite": 6,
    "bottles_haut": 3,
    "bottles_bas": 3,
    "notes": "",
    "created_at": "2026-03-08 08:21:27",
    "groupe_id": null
  },
  {
    "id": 16,
    "loge_id": "M1-C1-B4-L4",
    "mur": 1,
    "col_beton": 1,
    "bloc": 4,
    "loge": 4,
    "domaine": "Domaine Rapet",
    "appellation": "Ladoix",
    "millesime": "2017",
    "boire_a_partir": 2022,
    "boire_avant": null,
    "couleur": "rouge",
    "prix_unit": 16.5,
    "quantite": 4,
    "bottles_haut": 1,
    "bottles_bas": 3,
    "notes": "",
    "created_at": "2026-03-08 08:21:27",
    "groupe_id": null
  },
  {
    "id": 17,
    "loge_id": "M1-C2-B1-L1",
    "mur": 1,
    "col_beton": 2,
    "bloc": 1,
    "loge": 1,
    "domaine": "Fleur de Cros",
    "appellation": "Loupiac",
    "millesime": "2016",
    "boire_a_partir": 2026,
    "boire_avant": null,
    "couleur": "blanc",
    "prix_unit": 10.9,
    "quantite": 6,
    "bottles_haut": 3,
    "bottles_bas": 3,
    "notes": "",
    "created_at": "2026-03-08 08:21:27",
    "groupe_id": null
  },
  {
    "id": 18,
    "loge_id": "M1-C2-B1-L2",
    "mur": 1,
    "col_beton": 2,
    "bloc": 1,
    "loge": 2,
    "domaine": "Cht La Gardine",
    "appellation": "Rasteau",
    "millesime": "2018",
    "boire_a_partir": 2025,
    "boire_avant": null,
    "couleur": "rouge",
    "prix_unit": 14.75,
    "quantite": 5,
    "bottles_haut": 2,
    "bottles_bas": 3,
    "notes": "",
    "created_at": "2026-03-08 08:21:27",
    "groupe_id": null
  },
  {
    "id": 19,
    "loge_id": "M1-C2-B1-L3",
    "mur": 1,
    "col_beton": 2,
    "bloc": 1,
    "loge": 3,
    "domaine": "Domaine Deschamps",
    "appellation": "Pouilly Fumé Les Loges",
    "millesime": "2020",
    "boire_a_partir": 2024,
    "boire_avant": null,
    "couleur": "blanc",
    "prix_unit": 13.5,
    "quantite": 4,
    "bottles_haut": 1,
    "bottles_bas": 3,
    "notes": "",
    "created_at": "2026-03-08 08:21:27",
    "groupe_id": null
  },
  {
    "id": 20,
    "loge_id": "M1-C2-B2-L1",
    "mur": 1,
    "col_beton": 2,
    "bloc": 2,
    "loge": 1,
    "domaine": "Domaine Deschamps",
    "appellation": "Pouilly Fumé Les Loges",
    "millesime": "2018",
    "boire_a_partir": 2022,
    "boire_avant": null,
    "couleur": "blanc",
    "prix_unit": 11.0,
    "quantite": 1,
    "bottles_haut": 0,
    "bottles_bas": 1,
    "notes": "",
    "created_at": "2026-03-08 08:21:27",
    "groupe_id": null
  },
  {
    "id": 21,
    "loge_id": "M1-C2-B2-L2",
    "mur": 1,
    "col_beton": 2,
    "bloc": 2,
    "loge": 2,
    "domaine": "Dom A Bonhomme",
    "appellation": "Viré Clessé",
    "millesime": "2023",
    "boire_a_partir": 2028,
    "boire_avant": null,
    "couleur": "blanc",
    "prix_unit": 15.7,
    "quantite": 6,
    "bottles_haut": 3,
    "bottles_bas": 3,
    "notes": "",
    "created_at": "2026-03-08 08:21:27",
    "groupe_id": null
  },
  {
    "id": 22,
    "loge_id": "M1-C2-B2-L3",
    "mur": 1,
    "col_beton": 2,
    "bloc": 2,
    "loge": 3,
    "domaine": "Domaine Cheveau",
    "appellation": "Macon Fuissé",
    "millesime": "2018",
    "boire_a_partir": 2022,
    "boire_avant": null,
    "couleur": "blanc",
    "prix_unit": 9.2,
    "quantite": 1,
    "bottles_haut": 0,
    "bottles_bas": 1,
    "notes": "",
    "created_at": "2026-03-08 08:21:27",
    "groupe_id": null
  },
  {
    "id": 23,
    "loge_id": "M1-C2-B2-L4",
    "mur": 1,
    "col_beton": 2,
    "bloc": 2,
    "loge": 4,
    "domaine": "Domaine Deschamps",
    "appellation": "Pouilly Fumé Les Loges",
    "millesime": "2020",
    "boire_a_partir": 2024,
    "boire_avant": null,
    "couleur": "blanc",
    "prix_unit": 13.5,
    "quantite": 3,
    "bottles_haut": 0,
    "bottles_bas": 3,
    "notes": "",
    "created_at": "2026-03-08 08:21:27",
    "groupe_id": null
  },
  {
    "id": 24,
    "loge_id": "M1-C2-B3-L1",
    "mur": 1,
    "col_beton": 2,
    "bloc": 3,
    "loge": 1,
    "domaine": "Domaine Cheveau",
    "appellation": "Saint Véran",
    "millesime": "2017",
    "boire_a_partir": 2022,
    "boire_avant": null,
    "couleur": "blanc",
    "prix_unit": 11.5,
    "quantite": 3,
    "bottles_haut": 0,
    "bottles_bas": 3,
    "notes": "",
    "created_at": "2026-03-08 08:21:27",
    "groupe_id": null
  },
  {
    "id": 25,
    "loge_id": "M1-C2-B3-L2",
    "mur": 1,
    "col_beton": 2,
    "bloc": 3,
    "loge": 2,
    "domaine": "Gautheron",
    "appellation": "Chablis",
    "millesime": "2023",
    "boire_a_partir": 2028,
    "boire_avant": null,
    "couleur": "blanc",
    "prix_unit": 13.5,
    "quantite": 6,
    "bottles_haut": 3,
    "bottles_bas": 3,
    "notes": "",
    "created_at": "2026-03-08 08:21:27",
    "groupe_id": null
  },
  {
    "id": 26,
    "loge_id": "M1-C2-B3-L3",
    "mur": 1,
    "col_beton": 2,
    "bloc": 3,
    "loge": 3,
    "domaine": "Pernand-Vergelesses",
    "appellation": "1 er Cru Les Frétilles",
    "millesime": "2016",
    "boire_a_partir": 2022,
    "boire_avant": null,
    "couleur": "rouge",
    "prix_unit": 23.0,
    "quantite": 3,
    "bottles_haut": 0,
    "bottles_bas": 3,
    "notes": "",
    "created_at": "2026-03-08 08:21:27",
    "groupe_id": null
  },
  {
    "id": 27,
    "loge_id": "M1-C2-B4-L3",
    "mur": 1,
    "col_beton": 2,
    "bloc": 4,
    "loge": 3,
    "domaine": "Domaine Mouty",
    "appellation": "Rambaud Blanc",
    "millesime": "2023",
    "boire_a_partir": null,
    "boire_avant": null,
    "couleur": "blanc",
    "prix_unit": 10.0,
    "quantite": 6,
    "bottles_haut": 3,
    "bottles_bas": 3,
    "notes": "",
    "created_at": "2026-03-08 08:21:27",
    "groupe_id": null
  },
  {
    "id": 28,
    "loge_id": "M1-C2-B4-L4",
    "mur": 1,
    "col_beton": 2,
    "bloc": 4,
    "loge": 4,
    "domaine": "Domaine Deschamps",
    "appellation": "Pouilly Fumé Les Loges",
    "millesime": "2017",
    "boire_a_partir": 2022,
    "boire_avant": null,
    "couleur": "blanc",
    "prix_unit": 13.0,
    "quantite": 3,
    "bottles_haut": 0,
    "bottles_bas": 3,
    "notes": "",
    "created_at": "2026-03-08 08:21:27",
    "groupe_id": null
  },
  {
    "id": 29,
    "loge_id": "M1-C3-B1-L1",
    "mur": 1,
    "col_beton": 3,
    "bloc": 1,
    "loge": 1,
    "domaine": "Fleur Milon",
    "appellation": "Pauillac",
    "millesime": "2002",
    "boire_a_partir": null,
    "boire_avant": null,
    "couleur": "rouge",
    "prix_unit": 10.37,
    "quantite": 3,
    "bottles_haut": 0,
    "bottles_bas": 3,
    "notes": "",
    "created_at": "2026-03-08 08:21:27",
    "groupe_id": null
  },
  {
    "id": 30,
    "loge_id": "M1-C3-B1-L2",
    "mur": 1,
    "col_beton": 3,
    "bloc": 1,
    "loge": 2,
    "domaine": "Fleur Milon",
    "appellation": "Pauillac",
    "millesime": "2002",
    "boire_a_partir": null,
    "boire_avant": null,
    "couleur": "rouge",
    "prix_unit": 10.37,
    "quantite": 6,
    "bottles_haut": 3,
    "bottles_bas": 3,
    "notes": "",
    "created_at": "2026-03-08 08:21:27",
    "groupe_id": null
  },
  {
    "id": 31,
    "loge_id": "M1-C3-B1-L3",
    "mur": 1,
    "col_beton": 3,
    "bloc": 1,
    "loge": 3,
    "domaine": "La Fon du Berger",
    "appellation": "Pauillac",
    "millesime": "2014",
    "boire_a_partir": 2024,
    "boire_avant": null,
    "couleur": "rouge",
    "prix_unit": 15.5,
    "quantite": 3,
    "bottles_haut": 0,
    "bottles_bas": 3,
    "notes": "",
    "created_at": "2026-03-08 08:21:27",
    "groupe_id": null
  },
  {
    "id": 32,
    "loge_id": "M1-C3-B1-L4",
    "mur": 1,
    "col_beton": 3,
    "bloc": 1,
    "loge": 4,
    "domaine": "Ch Labastide Dauzac",
    "appellation": "Margaux",
    "millesime": "2005",
    "boire_a_partir": null,
    "boire_avant": null,
    "couleur": "rouge",
    "prix_unit": 23.93,
    "quantite": 6,
    "bottles_haut": 3,
    "bottles_bas": 3,
    "notes": "",
    "created_at": "2026-03-08 08:21:27",
    "groupe_id": null
  },
  {
    "id": 33,
    "loge_id": "M1-C3-B2-L1",
    "mur": 1,
    "col_beton": 3,
    "bloc": 2,
    "loge": 1,
    "domaine": "Domaine Mouty",
    "appellation": "Extrait de Rambaud",
    "millesime": "2018",
    "boire_a_partir": 2024,
    "boire_avant": null,
    "couleur": "rouge",
    "prix_unit": 10.5,
    "quantite": 5,
    "bottles_haut": 1,
    "bottles_bas": 3,
    "notes": "",
    "created_at": "2026-03-08 08:21:27",
    "groupe_id": null
  },
  {
    "id": 34,
    "loge_id": "M1-C3-B2-L2",
    "mur": 1,
    "col_beton": 3,
    "bloc": 2,
    "loge": 2,
    "domaine": "Domaine de Viaud",
    "appellation": "Lalande de Pomerol",
    "millesime": "2014",
    "boire_a_partir": 2022,
    "boire_avant": null,
    "couleur": "rouge",
    "prix_unit": 18.0,
    "quantite": 5,
    "bottles_haut": 2,
    "bottles_bas": 3,
    "notes": "",
    "created_at": "2026-03-08 08:21:27",
    "groupe_id": null
  },
  {
    "id": 35,
    "loge_id": "M1-C3-B2-L3",
    "mur": 1,
    "col_beton": 3,
    "bloc": 2,
    "loge": 3,
    "domaine": "Ch La Fon Du Berger",
    "appellation": "Pauillac",
    "millesime": "2015",
    "boire_a_partir": null,
    "boire_avant": null,
    "couleur": "rouge",
    "prix_unit": 15.5,
    "quantite": 4,
    "bottles_haut": 1,
    "bottles_bas": 3,
    "notes": "",
    "created_at": "2026-03-08 08:21:27",
    "groupe_id": null
  },
  {
    "id": 36,
    "loge_id": "M1-C3-B2-L4",
    "mur": 1,
    "col_beton": 3,
    "bloc": 2,
    "loge": 4,
    "domaine": "Château de la Tour",
    "appellation": "Clos Vougeot",
    "millesime": "2004",
    "boire_a_partir": null,
    "boire_avant": null,
    "couleur": "rouge",
    "prix_unit": 65.0,
    "quantite": 3,
    "bottles_haut": 0,
    "bottles_bas": 3,
    "notes": "",
    "created_at": "2026-03-08 08:21:27",
    "groupe_id": null
  },
  {
    "id": 37,
    "loge_id": "M1-C3-B3-L1",
    "mur": 1,
    "col_beton": 3,
    "bloc": 3,
    "loge": 1,
    "domaine": "Ch. La Fon du Berger",
    "appellation": "Haut Médoc",
    "millesime": "2019",
    "boire_a_partir": 2029,
    "boire_avant": null,
    "couleur": "rouge",
    "prix_unit": 7.5,
    "quantite": 6,
    "bottles_haut": 3,
    "bottles_bas": 3,
    "notes": "",
    "created_at": "2026-03-08 08:21:27",
    "groupe_id": null
  },
  {
    "id": 38,
    "loge_id": "M1-C3-B3-L2",
    "mur": 1,
    "col_beton": 3,
    "bloc": 3,
    "loge": 2,
    "domaine": "Ch. La Fon du Berger",
    "appellation": "Haut Médoc",
    "millesime": "2019",
    "boire_a_partir": 2029,
    "boire_avant": null,
    "couleur": "rouge",
    "prix_unit": 7.5,
    "quantite": 6,
    "bottles_haut": 3,
    "bottles_bas": 3,
    "notes": "",
    "created_at": "2026-03-08 08:21:27",
    "groupe_id": null
  },
  {
    "id": 39,
    "loge_id": "M1-C3-B3-L3",
    "mur": 1,
    "col_beton": 3,
    "bloc": 3,
    "loge": 3,
    "domaine": "La Fon du Berger",
    "appellation": "Haut Médoc",
    "millesime": "2017",
    "boire_a_partir": 2024,
    "boire_avant": null,
    "couleur": "rouge",
    "prix_unit": 7.5,
    "quantite": 6,
    "bottles_haut": 3,
    "bottles_bas": 3,
    "notes": "",
    "created_at": "2026-03-08 08:21:27",
    "groupe_id": null
  },
  {
    "id": 40,
    "loge_id": "M1-C3-B3-L4",
    "mur": 1,
    "col_beton": 3,
    "bloc": 3,
    "loge": 4,
    "domaine": "Ch. La Fon du Berger",
    "appellation": "Haut Médoc",
    "millesime": "2019",
    "boire_a_partir": 2029,
    "boire_avant": null,
    "couleur": "rouge",
    "prix_unit": 7.5,
    "quantite": 6,
    "bottles_haut": 3,
    "bottles_bas": 3,
    "notes": "",
    "created_at": "2026-03-08 08:21:27",
    "groupe_id": null
  },
  {
    "id": 41,
    "loge_id": "M1-C3-B4-L1",
    "mur": 1,
    "col_beton": 3,
    "bloc": 4,
    "loge": 1,
    "domaine": "La Fon du Berger",
    "appellation": "Haut Médoc",
    "millesime": "2017",
    "boire_a_partir": 2024,
    "boire_avant": null,
    "couleur": "rouge",
    "prix_unit": 7.5,
    "quantite": 3,
    "bottles_haut": 0,
    "bottles_bas": 3,
    "notes": "",
    "created_at": "2026-03-08 08:21:27",
    "groupe_id": null
  },
  {
    "id": 42,
    "loge_id": "M1-C3-B4-L2",
    "mur": 1,
    "col_beton": 3,
    "bloc": 4,
    "loge": 2,
    "domaine": "La Fon du Berger",
    "appellation": "Haut Médoc",
    "millesime": "2017",
    "boire_a_partir": 2024,
    "boire_avant": null,
    "couleur": "rouge",
    "prix_unit": 7.5,
    "quantite": 2,
    "bottles_haut": 0,
    "bottles_bas": 2,
    "notes": "",
    "created_at": "2026-03-08 08:21:27",
    "groupe_id": null
  },
  {
    "id": 43,
    "loge_id": "M1-C3-B4-L3",
    "mur": 1,
    "col_beton": 3,
    "bloc": 4,
    "loge": 3,
    "domaine": "La Fon du Berger",
    "appellation": "Pauillac",
    "millesime": "2016",
    "boire_a_partir": 2025,
    "boire_avant": null,
    "couleur": "rouge",
    "prix_unit": 17.0,
    "quantite": 6,
    "bottles_haut": 3,
    "bottles_bas": 3,
    "notes": "",
    "created_at": "2026-03-08 08:21:27",
    "groupe_id": null
  },
  {
    "id": 44,
    "loge_id": "M1-C3-B4-L4",
    "mur": 1,
    "col_beton": 3,
    "bloc": 4,
    "loge": 4,
    "domaine": "Ch La Fon du Berger",
    "appellation": "Pauillac",
    "millesime": "2010",
    "boire_a_partir": 2020,
    "boire_avant": null,
    "couleur": "rouge",
    "prix_unit": 15.5,
    "quantite": 5,
    "bottles_haut": 2,
    "bottles_bas": 3,
    "notes": "",
    "created_at": "2026-03-08 08:21:27",
    "groupe_id": null
  },
  {
    "id": 45,
    "loge_id": "M2-C1-B1-L1",
    "mur": 2,
    "col_beton": 1,
    "bloc": 1,
    "loge": 1,
    "domaine": "David DUBAND",
    "appellation": "Vosne-Romanée",
    "millesime": "2014",
    "boire_a_partir": 2022,
    "boire_avant": null,
    "couleur": "rouge",
    "prix_unit": 28.98,
    "quantite": 2,
    "bottles_haut": 0,
    "bottles_bas": 2,
    "notes": "",
    "created_at": "2026-03-08 08:21:27",
    "groupe_id": null
  },
  {
    "id": 46,
    "loge_id": "M2-C1-B1-L2",
    "mur": 2,
    "col_beton": 1,
    "bloc": 1,
    "loge": 2,
    "domaine": "Haut Marbuzet",
    "appellation": "St Estèphe",
    "millesime": "2002",
    "boire_a_partir": null,
    "boire_avant": null,
    "couleur": "rouge",
    "prix_unit": 19.0,
    "quantite": 5,
    "bottles_haut": 2,
    "bottles_bas": 3,
    "notes": "",
    "created_at": "2026-03-08 08:21:27",
    "groupe_id": null
  },
  {
    "id": 47,
    "loge_id": "M2-C1-B1-L3",
    "mur": 2,
    "col_beton": 1,
    "bloc": 1,
    "loge": 3,
    "domaine": "Cht du Barry",
    "appellation": "Saint Emilion G C",
    "millesime": "2017",
    "boire_a_partir": 2027,
    "boire_avant": null,
    "couleur": "rouge",
    "prix_unit": 17.0,
    "quantite": 6,
    "bottles_haut": 3,
    "bottles_bas": 3,
    "notes": "",
    "created_at": "2026-03-08 08:21:27",
    "groupe_id": null
  },
  {
    "id": 48,
    "loge_id": "M2-C1-B1-L4",
    "mur": 2,
    "col_beton": 1,
    "bloc": 1,
    "loge": 4,
    "domaine": "Cht du Barry",
    "appellation": "Saint Emilion G C",
    "millesime": "2018",
    "boire_a_partir": 2028,
    "boire_avant": null,
    "couleur": "rouge",
    "prix_unit": 18.0,
    "quantite": 6,
    "bottles_haut": 3,
    "bottles_bas": 3,
    "notes": "",
    "created_at": "2026-03-08 08:21:27",
    "groupe_id": null
  },
  {
    "id": 49,
    "loge_id": "M2-C1-B2-L1",
    "mur": 2,
    "col_beton": 1,
    "bloc": 2,
    "loge": 1,
    "domaine": "Cht du Barry",
    "appellation": "Saint Emilion G C",
    "millesime": "2016",
    "boire_a_partir": 2026,
    "boire_avant": null,
    "couleur": "rouge",
    "prix_unit": 16.0,
    "quantite": 6,
    "bottles_haut": 3,
    "bottles_bas": 3,
    "notes": "",
    "created_at": "2026-03-08 08:21:27",
    "groupe_id": null
  },
  {
    "id": 50,
    "loge_id": "M2-C1-B2-L2",
    "mur": 2,
    "col_beton": 1,
    "bloc": 2,
    "loge": 2,
    "domaine": "Ch. Du Barry",
    "appellation": "St Emilion Grd Cru",
    "millesime": "2015",
    "boire_a_partir": 2025,
    "boire_avant": null,
    "couleur": "rouge",
    "prix_unit": 16.0,
    "quantite": 5,
    "bottles_haut": 2,
    "bottles_bas": 3,
    "notes": "",
    "created_at": "2026-03-08 08:21:27",
    "groupe_id": null
  },
  {
    "id": 51,
    "loge_id": "M2-C1-B2-L3",
    "mur": 2,
    "col_beton": 1,
    "bloc": 2,
    "loge": 3,
    "domaine": "Domaine Bouyer",
    "appellation": "Clos de la Cure  St Em G C",
    "millesime": "2020",
    "boire_a_partir": 2030,
    "boire_avant": null,
    "couleur": "rouge",
    "prix_unit": 17.5,
    "quantite": 6,
    "bottles_haut": 3,
    "bottles_bas": 3,
    "notes": "",
    "created_at": "2026-03-08 08:21:27",
    "groupe_id": null
  },
  {
    "id": 52,
    "loge_id": "M2-C1-B2-L4",
    "mur": 2,
    "col_beton": 1,
    "bloc": 2,
    "loge": 4,
    "domaine": "Ch. Du Barry",
    "appellation": "St Emilion Grd Cru",
    "millesime": "2015",
    "boire_a_partir": 2025,
    "boire_avant": null,
    "couleur": "rouge",
    "prix_unit": 16.0,
    "quantite": 6,
    "bottles_haut": 3,
    "bottles_bas": 3,
    "notes": "",
    "created_at": "2026-03-08 08:21:27",
    "groupe_id": null
  },
  {
    "id": 53,
    "loge_id": "M2-C1-B3-L1",
    "mur": 2,
    "col_beton": 1,
    "bloc": 3,
    "loge": 1,
    "domaine": "Domaine Mouty",
    "appellation": "Extrait de Raimbaud",
    "millesime": "2022",
    "boire_a_partir": 2028,
    "boire_avant": null,
    "couleur": "rouge",
    "prix_unit": 11.5,
    "quantite": 6,
    "bottles_haut": 3,
    "bottles_bas": 3,
    "notes": "",
    "created_at": "2026-03-08 08:21:27",
    "groupe_id": null
  },
  {
    "id": 54,
    "loge_id": "M2-C1-B3-L2",
    "mur": 2,
    "col_beton": 1,
    "bloc": 3,
    "loge": 2,
    "domaine": "Ch. La Fon du Berger",
    "appellation": "Haut Médoc",
    "millesime": "2022",
    "boire_a_partir": 2032,
    "boire_avant": null,
    "couleur": "rouge",
    "prix_unit": 7.5,
    "quantite": 6,
    "bottles_haut": 3,
    "bottles_bas": 3,
    "notes": "",
    "created_at": "2026-03-08 08:21:27",
    "groupe_id": null
  },
  {
    "id": 55,
    "loge_id": "M2-C1-B3-L3",
    "mur": 2,
    "col_beton": 1,
    "bloc": 3,
    "loge": 3,
    "domaine": "Domaine Mouty",
    "appellation": "Extrait de Raimbaud",
    "millesime": "2021",
    "boire_a_partir": 2028,
    "boire_avant": null,
    "couleur": "rouge",
    "prix_unit": 11.5,
    "quantite": 6,
    "bottles_haut": 3,
    "bottles_bas": 3,
    "notes": "",
    "created_at": "2026-03-08 08:21:27",
    "groupe_id": null
  },
  {
    "id": 56,
    "loge_id": "M2-C1-B3-L4",
    "mur": 2,
    "col_beton": 1,
    "bloc": 3,
    "loge": 4,
    "domaine": "Ch. La Fon du Berger",
    "appellation": "Haut Médoc",
    "millesime": "2022",
    "boire_a_partir": 2032,
    "boire_avant": null,
    "couleur": "rouge",
    "prix_unit": 7.5,
    "quantite": 6,
    "bottles_haut": 3,
    "bottles_bas": 3,
    "notes": "",
    "created_at": "2026-03-08 08:21:27",
    "groupe_id": null
  },
  {
    "id": 57,
    "loge_id": "M2-C1-B4-L1",
    "mur": 2,
    "col_beton": 1,
    "bloc": 4,
    "loge": 1,
    "domaine": "Domaine Bournet",
    "appellation": "Cuvée Chris",
    "millesime": "2019",
    "boire_a_partir": null,
    "boire_avant": null,
    "couleur": "rouge",
    "prix_unit": 13.5,
    "quantite": 6,
    "bottles_haut": 3,
    "bottles_bas": 3,
    "notes": "",
    "created_at": "2026-03-08 08:21:27",
    "groupe_id": null
  },
  {
    "id": 58,
    "loge_id": "M2-C1-B4-L2",
    "mur": 2,
    "col_beton": 1,
    "bloc": 4,
    "loge": 2,
    "domaine": "Ch. La Fon du Berger",
    "appellation": "Haut Médoc",
    "millesime": "2022",
    "boire_a_partir": 2032,
    "boire_avant": null,
    "couleur": "rouge",
    "prix_unit": 7.5,
    "quantite": 6,
    "bottles_haut": 3,
    "bottles_bas": 3,
    "notes": "",
    "created_at": "2026-03-08 08:21:27",
    "groupe_id": null
  },
  {
    "id": 59,
    "loge_id": "M2-C1-B4-L3",
    "mur": 2,
    "col_beton": 1,
    "bloc": 4,
    "loge": 3,
    "domaine": "Domaine Bournet",
    "appellation": "Cuvée Chris",
    "millesime": "2016",
    "boire_a_partir": null,
    "boire_avant": null,
    "couleur": "rouge",
    "prix_unit": 13.5,
    "quantite": 6,
    "bottles_haut": 3,
    "bottles_bas": 3,
    "notes": "",
    "created_at": "2026-03-08 08:21:27",
    "groupe_id": null
  },
  {
    "id": 60,
    "loge_id": "M2-C1-B4-L4",
    "mur": 2,
    "col_beton": 1,
    "bloc": 4,
    "loge": 4,
    "domaine": "Domaine Bournet",
    "appellation": "Les Ambassadeurs",
    "millesime": "2016",
    "boire_a_partir": null,
    "boire_avant": null,
    "couleur": "rouge",
    "prix_unit": 18.5,
    "quantite": 5,
    "bottles_haut": 2,
    "bottles_bas": 3,
    "notes": "",
    "created_at": "2026-03-08 08:21:27",
    "groupe_id": null
  },
  {
    "id": 61,
    "loge_id": "M2-C2-B1-L1",
    "mur": 2,
    "col_beton": 2,
    "bloc": 1,
    "loge": 1,
    "domaine": "David DUBAND",
    "appellation": "Nuits St Georges",
    "millesime": "2014",
    "boire_a_partir": 2022,
    "boire_avant": null,
    "couleur": "rouge",
    "prix_unit": 30.67,
    "quantite": 5,
    "bottles_haut": 2,
    "bottles_bas": 3,
    "notes": "",
    "created_at": "2026-03-08 08:21:27",
    "groupe_id": null
  },
  {
    "id": 62,
    "loge_id": "M2-C2-B1-L2",
    "mur": 2,
    "col_beton": 2,
    "bloc": 1,
    "loge": 2,
    "domaine": "Domaine Mouty",
    "appellation": "Extrait de Rambaud",
    "millesime": "2017",
    "boire_a_partir": 2025,
    "boire_avant": null,
    "couleur": "rouge",
    "prix_unit": 10.5,
    "quantite": 6,
    "bottles_haut": 3,
    "bottles_bas": 3,
    "notes": "",
    "created_at": "2026-03-08 08:21:27",
    "groupe_id": null
  },
  {
    "id": 63,
    "loge_id": "M2-C2-B1-L3",
    "mur": 2,
    "col_beton": 2,
    "bloc": 1,
    "loge": 3,
    "domaine": "Tyrand - Elégance",
    "appellation": "Côtes du Rhone",
    "millesime": "2017",
    "boire_a_partir": 2022,
    "boire_avant": null,
    "couleur": "rouge",
    "prix_unit": 7.2,
    "quantite": 5,
    "bottles_haut": 2,
    "bottles_bas": 3,
    "notes": "",
    "created_at": "2026-03-08 08:21:27",
    "groupe_id": null
  },
  {
    "id": 64,
    "loge_id": "M2-C2-B1-L4",
    "mur": 2,
    "col_beton": 2,
    "bloc": 1,
    "loge": 4,
    "domaine": "Château Saint Roch",
    "appellation": "Lirac",
    "millesime": "2019",
    "boire_a_partir": 2027,
    "boire_avant": null,
    "couleur": "rouge",
    "prix_unit": 13.5,
    "quantite": 6,
    "bottles_haut": 3,
    "bottles_bas": 3,
    "notes": "",
    "created_at": "2026-03-08 08:21:27",
    "groupe_id": null
  },
  {
    "id": 65,
    "loge_id": "M2-C2-B2-L1",
    "mur": 2,
    "col_beton": 2,
    "bloc": 2,
    "loge": 1,
    "domaine": "Ch Pierre Minot",
    "appellation": "Vosne Romanée",
    "millesime": "2015",
    "boire_a_partir": null,
    "boire_avant": null,
    "couleur": "rouge",
    "prix_unit": 44.17,
    "quantite": 3,
    "bottles_haut": 0,
    "bottles_bas": 3,
    "notes": "",
    "created_at": "2026-03-08 08:21:27",
    "groupe_id": null
  },
  {
    "id": 66,
    "loge_id": "M2-C2-B2-L2",
    "mur": 2,
    "col_beton": 2,
    "bloc": 2,
    "loge": 2,
    "domaine": "Ch Pierre Minot",
    "appellation": "Chambolle Musigny",
    "millesime": "2015",
    "boire_a_partir": null,
    "boire_avant": null,
    "couleur": "rouge",
    "prix_unit": 44.17,
    "quantite": 3,
    "bottles_haut": 0,
    "bottles_bas": 3,
    "notes": "",
    "created_at": "2026-03-08 08:21:27",
    "groupe_id": null
  },
  {
    "id": 67,
    "loge_id": "M2-C2-B2-L3",
    "mur": 2,
    "col_beton": 2,
    "bloc": 2,
    "loge": 3,
    "domaine": "Domaine de Viaud Marius Bielle",
    "appellation": "Lalande de Pommerol",
    "millesime": "2015",
    "boire_a_partir": 2025,
    "boire_avant": null,
    "couleur": "rouge",
    "prix_unit": 19.0,
    "quantite": 6,
    "bottles_haut": 3,
    "bottles_bas": 3,
    "notes": "",
    "created_at": "2026-03-08 08:21:27",
    "groupe_id": null
  },
  {
    "id": 68,
    "loge_id": "M2-C2-B2-L4",
    "mur": 2,
    "col_beton": 2,
    "bloc": 2,
    "loge": 4,
    "domaine": "Domaine Mouty",
    "appellation": "Extrait de Rambaud",
    "millesime": "2022",
    "boire_a_partir": 2025,
    "boire_avant": null,
    "couleur": "rouge",
    "prix_unit": 10.5,
    "quantite": 1,
    "bottles_haut": 0,
    "bottles_bas": 1,
    "notes": "",
    "created_at": "2026-03-08 08:21:27",
    "groupe_id": null
  },
  {
    "id": 69,
    "loge_id": "M2-C2-B3-L1",
    "mur": 2,
    "col_beton": 2,
    "bloc": 3,
    "loge": 1,
    "domaine": "Cht Lafargue",
    "appellation": "Pessac Leognan",
    "millesime": "2019",
    "boire_a_partir": 2026,
    "boire_avant": null,
    "couleur": "rouge",
    "prix_unit": 15.0,
    "quantite": 5,
    "bottles_haut": 2,
    "bottles_bas": 3,
    "notes": "",
    "created_at": "2026-03-08 08:21:27",
    "groupe_id": null
  },
  {
    "id": 70,
    "loge_id": "M2-C2-B3-L2",
    "mur": 2,
    "col_beton": 2,
    "bloc": 3,
    "loge": 2,
    "domaine": "David DUBAND",
    "appellation": "Vosne-Romanée",
    "millesime": "2014",
    "boire_a_partir": 2022,
    "boire_avant": null,
    "couleur": "rouge",
    "prix_unit": 28.98,
    "quantite": 5,
    "bottles_haut": 2,
    "bottles_bas": 3,
    "notes": "",
    "created_at": "2026-03-08 08:21:27",
    "groupe_id": null
  },
  {
    "id": 71,
    "loge_id": "M2-C2-B3-L3",
    "mur": 2,
    "col_beton": 2,
    "bloc": 3,
    "loge": 3,
    "domaine": "Domaine Bournet",
    "appellation": "Les Ambassadeurs",
    "millesime": "2016",
    "boire_a_partir": 2028,
    "boire_avant": null,
    "couleur": "rouge",
    "prix_unit": 19.5,
    "quantite": 5,
    "bottles_haut": 2,
    "bottles_bas": 3,
    "notes": "",
    "created_at": "2026-03-08 08:21:27",
    "groupe_id": null
  },
  {
    "id": 72,
    "loge_id": "M2-C2-B3-L4",
    "mur": 2,
    "col_beton": 2,
    "bloc": 3,
    "loge": 4,
    "domaine": "Domaine Bournet",
    "appellation": "Les Ambassadeurs",
    "millesime": "2016",
    "boire_a_partir": 2028,
    "boire_avant": null,
    "couleur": "rouge",
    "prix_unit": 19.5,
    "quantite": 2,
    "bottles_haut": 0,
    "bottles_bas": 3,
    "notes": "",
    "created_at": "2026-03-08 08:21:27",
    "groupe_id": null
  },
  {
    "id": 73,
    "loge_id": "M2-C2-B4-L1",
    "mur": 2,
    "col_beton": 2,
    "bloc": 4,
    "loge": 1,
    "domaine": "Domaine Bournet",
    "appellation": "Nombre d'Or",
    "millesime": "2012",
    "boire_a_partir": null,
    "boire_avant": null,
    "couleur": "rouge",
    "prix_unit": 35.0,
    "quantite": 6,
    "bottles_haut": 3,
    "bottles_bas": 3,
    "notes": "",
    "created_at": "2026-03-08 08:21:27",
    "groupe_id": null
  },
  {
    "id": 74,
    "loge_id": "M2-C2-B4-L2",
    "mur": 2,
    "col_beton": 2,
    "bloc": 4,
    "loge": 2,
    "domaine": "David DUBAND",
    "appellation": "Nuits St Georges",
    "millesime": "2014",
    "boire_a_partir": 2022,
    "boire_avant": null,
    "couleur": "rouge",
    "prix_unit": 30.67,
    "quantite": 4,
    "bottles_haut": 1,
    "bottles_bas": 3,
    "notes": "",
    "created_at": "2026-03-08 08:21:27",
    "groupe_id": null
  },
  {
    "id": 75,
    "loge_id": "M2-C2-B4-L3",
    "mur": 2,
    "col_beton": 2,
    "bloc": 4,
    "loge": 3,
    "domaine": "Jerome Galeyrand",
    "appellation": "Gevrey Chambertin",
    "millesime": "2003",
    "boire_a_partir": null,
    "boire_avant": null,
    "couleur": "rouge",
    "prix_unit": 25.05,
    "quantite": 2,
    "bottles_haut": 0,
    "bottles_bas": 2,
    "notes": "",
    "created_at": "2026-03-08 08:21:27",
    "groupe_id": null
  },
  {
    "id": 76,
    "loge_id": "M2-C2-B4-L4",
    "mur": 2,
    "col_beton": 2,
    "bloc": 4,
    "loge": 4,
    "domaine": "Domaine Bournet",
    "appellation": "Rosé",
    "millesime": "2023",
    "boire_a_partir": null,
    "boire_avant": null,
    "couleur": "rose",
    "prix_unit": 9.0,
    "quantite": 3,
    "bottles_haut": 0,
    "bottles_bas": 3,
    "notes": "",
    "created_at": "2026-03-08 08:21:27",
    "groupe_id": null
  },
  {
    "id": 77,
    "loge_id": "M2-C3-B1-L1",
    "mur": 2,
    "col_beton": 3,
    "bloc": 1,
    "loge": 1,
    "domaine": "Porto  Villiera",
    "appellation": "Afrique du Sud",
    "millesime": "1997",
    "boire_a_partir": null,
    "boire_avant": null,
    "couleur": "porto",
    "prix_unit": 11.06,
    "quantite": 5,
    "bottles_haut": 2,
    "bottles_bas": 3,
    "notes": "",
    "created_at": "2026-03-08 08:21:27",
    "groupe_id": null
  },
  {
    "id": 78,
    "loge_id": "M2-C3-B1-L2",
    "mur": 2,
    "col_beton": 3,
    "bloc": 1,
    "loge": 2,
    "domaine": "",
    "appellation": "",
    "millesime": "",
    "boire_a_partir": null,
    "boire_avant": null,
    "couleur": "",
    "prix_unit": 0.0,
    "quantite": 0,
    "bottles_haut": 0,
    "bottles_bas": 0,
    "notes": "",
    "created_at": "2026-03-08 08:21:27",
    "groupe_id": null
  },
  {
    "id": 79,
    "loge_id": "M2-C3-B1-L3",
    "mur": 2,
    "col_beton": 3,
    "bloc": 1,
    "loge": 3,
    "domaine": "Cht de la Gardine",
    "appellation": "Côte du Rhone",
    "millesime": "2023",
    "boire_a_partir": 2030,
    "boire_avant": null,
    "couleur": "rouge",
    "prix_unit": 10.8,
    "quantite": 6,
    "bottles_haut": 3,
    "bottles_bas": 3,
    "notes": "",
    "created_at": "2026-03-08 08:21:27",
    "groupe_id": null
  },
  {
    "id": 80,
    "loge_id": "M2-C3-B1-L4",
    "mur": 2,
    "col_beton": 3,
    "bloc": 1,
    "loge": 4,
    "domaine": "",
    "appellation": "divers",
    "millesime": "",
    "boire_a_partir": null,
    "boire_avant": null,
    "couleur": "",
    "prix_unit": 0.0,
    "quantite": 6,
    "bottles_haut": 3,
    "bottles_bas": 3,
    "notes": "",
    "created_at": "2026-03-08 08:21:27",
    "groupe_id": null
  },
  {
    "id": 81,
    "loge_id": "M2-C3-B2-L1",
    "mur": 2,
    "col_beton": 3,
    "bloc": 2,
    "loge": 1,
    "domaine": "Dom Mouty",
    "appellation": "Extrait de Rambaud",
    "millesime": "2023",
    "boire_a_partir": 2028,
    "boire_avant": null,
    "couleur": "rouge",
    "prix_unit": 11.5,
    "quantite": 6,
    "bottles_haut": 3,
    "bottles_bas": 3,
    "notes": "",
    "created_at": "2026-03-08 08:21:27",
    "groupe_id": null
  },
  {
    "id": 82,
    "loge_id": "M2-C3-B2-L2",
    "mur": 2,
    "col_beton": 3,
    "bloc": 2,
    "loge": 2,
    "domaine": "Domaine Mouty",
    "appellation": "Gd Beau Séjour Pomerol",
    "millesime": "2023",
    "boire_a_partir": 2035,
    "boire_avant": null,
    "couleur": "rouge",
    "prix_unit": 44.0,
    "quantite": 6,
    "bottles_haut": 3,
    "bottles_bas": 3,
    "notes": "",
    "created_at": "2026-03-08 08:21:27",
    "groupe_id": null
  },
  {
    "id": 83,
    "loge_id": "M2-C3-B2-L3",
    "mur": 2,
    "col_beton": 3,
    "bloc": 2,
    "loge": 3,
    "domaine": "François Cazin",
    "appellation": "Crémant de Loire",
    "millesime": "2021",
    "boire_a_partir": null,
    "boire_avant": null,
    "couleur": "champagne",
    "prix_unit": 9.0,
    "quantite": 4,
    "bottles_haut": 1,
    "bottles_bas": 3,
    "notes": "",
    "created_at": "2026-03-08 08:21:27",
    "groupe_id": null
  },
  {
    "id": 84,
    "loge_id": "M2-C3-B2-L4",
    "mur": 2,
    "col_beton": 3,
    "bloc": 2,
    "loge": 4,
    "domaine": "Domaine Bournet",
    "appellation": "Blanc Pét",
    "millesime": "2021",
    "boire_a_partir": 2028,
    "boire_avant": null,
    "couleur": "blanc",
    "prix_unit": 12.0,
    "quantite": 4,
    "bottles_haut": 1,
    "bottles_bas": 3,
    "notes": "",
    "created_at": "2026-03-08 08:21:27",
    "groupe_id": null
  },
  {
    "id": 85,
    "loge_id": "M2-C3-B3-L1",
    "mur": 2,
    "col_beton": 3,
    "bloc": 3,
    "loge": 1,
    "domaine": "",
    "appellation": "divers",
    "millesime": "",
    "boire_a_partir": null,
    "boire_avant": null,
    "couleur": "",
    "prix_unit": 0.0,
    "quantite": 6,
    "bottles_haut": 3,
    "bottles_bas": 3,
    "notes": "",
    "created_at": "2026-03-08 08:21:27",
    "groupe_id": null
  },
  {
    "id": 86,
    "loge_id": "M2-C3-B3-L2",
    "mur": 2,
    "col_beton": 3,
    "bloc": 3,
    "loge": 2,
    "domaine": "",
    "appellation": "divers",
    "millesime": "",
    "boire_a_partir": null,
    "boire_avant": null,
    "couleur": "",
    "prix_unit": 0.0,
    "quantite": 6,
    "bottles_haut": 3,
    "bottles_bas": 3,
    "notes": "",
    "created_at": "2026-03-08 08:21:27",
    "groupe_id": null
  },
  {
    "id": 87,
    "loge_id": "M2-C3-B3-L3",
    "mur": 2,
    "col_beton": 3,
    "bloc": 3,
    "loge": 3,
    "domaine": "",
    "appellation": "divers",
    "millesime": "",
    "boire_a_partir": null,
    "boire_avant": null,
    "couleur": "",
    "prix_unit": 0.0,
    "quantite": 6,
    "bottles_haut": 3,
    "bottles_bas": 3,
    "notes": "",
    "created_at": "2026-03-08 08:21:27",
    "groupe_id": null
  },
  {
    "id": 88,
    "loge_id": "M2-C3-B3-L4",
    "mur": 2,
    "col_beton": 3,
    "bloc": 3,
    "loge": 4,
    "domaine": "",
    "appellation": "divers",
    "millesime": "",
    "boire_a_partir": null,
    "boire_avant": null,
    "couleur": "",
    "prix_unit": 0.0,
    "quantite": 6,
    "bottles_haut": 3,
    "bottles_bas": 3,
    "notes": "",
    "created_at": "2026-03-08 08:21:27",
    "groupe_id": null
  },
  {
    "id": 89,
    "loge_id": "M2-C3-B4-L2",
    "mur": 2,
    "col_beton": 3,
    "bloc": 4,
    "loge": 2,
    "domaine": "",
    "appellation": "divers",
    "millesime": "",
    "boire_a_partir": null,
    "boire_avant": null,
    "couleur": "",
    "prix_unit": 0.0,
    "quantite": 4,
    "bottles_haut": 1,
    "bottles_bas": 3,
    "notes": "",
    "created_at": "2026-03-08 08:21:27",
    "groupe_id": null
  },
  {
    "id": 90,
    "loge_id": "M2-C3-B4-L3",
    "mur": 2,
    "col_beton": 3,
    "bloc": 4,
    "loge": 3,
    "domaine": "Champagne",
    "appellation": "Boutillez",
    "millesime": "2020",
    "boire_a_partir": null,
    "boire_avant": null,
    "couleur": "champagne",
    "prix_unit": 18.5,
    "quantite": 4,
    "bottles_haut": 1,
    "bottles_bas": 3,
    "notes": "",
    "created_at": "2026-03-08 08:21:27",
    "groupe_id": null
  },
  {
    "id": 91,
    "loge_id": "M2-C3-B4-L4",
    "mur": 2,
    "col_beton": 3,
    "bloc": 4,
    "loge": 4,
    "domaine": "Ch Pierre Minot",
    "appellation": "Morey St Denis",
    "millesime": "2015",
    "boire_a_partir": null,
    "boire_avant": null,
    "couleur": "rouge",
    "prix_unit": 44.17,
    "quantite": 3,
    "bottles_haut": 0,
    "bottles_bas": 3,
    "notes": "",
    "created_at": "2026-03-08 08:21:27",
    "groupe_id": null
  }
]